README
setup.py
maliciouspackage/__init__.py
maliciouspackage.egg-info/PKG-INFO
maliciouspackage.egg-info/SOURCES.txt
maliciouspackage.egg-info/dependency_links.txt
maliciouspackage.egg-info/not-zip-safe
maliciouspackage.egg-info/top_level.txt