Metadata-Version: 1.0
Name: maliciouspackage
Version: 0.4
Summary: Malicious Python package
Home-page: http://laforge.uk/maliciouspackage
Author: Laforge
Author-email: laforge@wearehackerone.com
License: MIT
Platform: UNKNOWN
